core_evals/safety_eval/__init__.py
core_evals/safety_eval/framework.yml
core_evals/safety_eval/framework_entrypoint.py
core_evals/safety_eval/output.py
nvidia_safety_harness-25.11.dist-info/licenses/LICENSE
safety_eval/__init__.py
safety_eval/callbacks.py
safety_eval/configs.py
safety_eval/main.py
safety_eval/run_inference.py
safety_eval/aegis_v2/__init__.py
safety_eval/aegis_v2/handler.py
safety_eval/aegis_v2/utils.py
safety_eval/wildguard/__init__.py
safety_eval/wildguard/handler.py
safety_eval/wildguard/wildguard_dataclasses.py
nvidia_safety_harness-25.11.dist-info/METADATA
nvidia_safety_harness-25.11.dist-info/WHEEL
nvidia_safety_harness-25.11.dist-info/entry_points.txt
nvidia_safety_harness-25.11.dist-info/top_level.txt
nvidia_safety_harness-25.11.dist-info/RECORD
