Metadata-Version: 2.4
Name: nvidia-safety-harness
Version: 25.11
Summary: Content safety evaluation tool - packaged by NVIDIA
Author: Prasoon Varshney, Makesh Narsimhan Sreedhar, Yoshi Suhara, Katherine Luna, Varun Singh, Christopher Parisien, Eileen Long
License: 
Classifier: Development Status :: 5 - Production/Stable
Classifier: Programming Language :: Python :: 3
Classifier: License :: OSI Approved :: Apache Software License
Classifier: Operating System :: OS Independent
Requires-Python: >=3.10
License-File: LICENSE
Requires-Dist: langchain
Requires-Dist: langchain_openai
Requires-Dist: more_itertools
Requires-Dist: pandas>=2.2.3
Requires-Dist: datasets>=2.19.1
Requires-Dist: rich>=14.0.0
Requires-Dist: omegaconf>=2.3.0
Requires-Dist: jinja2
Requires-Dist: flask
Requires-Dist: structlog
Requires-Dist: psutil
Requires-Dist: transformers
Requires-Dist: nemo-evaluator
Dynamic: license-file
